usr_r16/__init__.py
usr_r16/protocol.py
usr_r16-0.0.4.dist-info/LICENSE
usr_r16-0.0.4.dist-info/METADATA
usr_r16-0.0.4.dist-info/WHEEL
usr_r16-0.0.4.dist-info/top_level.txt
usr_r16-0.0.4.dist-info/RECORD
